nem_ed25519_rust.cp36-win_amd64.pyd
nem_ed25519_rust-1.0.0rc4.dist-info/DESCRIPTION.rst
nem_ed25519_rust-1.0.0rc4.dist-info/METADATA
nem_ed25519_rust-1.0.0rc4.dist-info/RECORD
nem_ed25519_rust-1.0.0rc4.dist-info/WHEEL
nem_ed25519_rust-1.0.0rc4.dist-info/metadata.json
nem_ed25519_rust-1.0.0rc4.dist-info/top_level.txt
