Metadata-Version: 2.0
Name: nem-ed25519-rust
Version: 1.0.0rc4
Summary: UNKNOWN
Home-page: https://github.com/namuyan/ed25519-dalek
License: BSD-3
Platform: UNKNOWN
Classifier: License :: OSI Approved :: BSD License
Classifier: Programming Language :: Python :: 3
Classifier: Programming Language :: Rust
